signaturesnet/__init__.py
signaturesnet/train_classifier.py
signaturesnet/train_errorfinder.py
signaturesnet/train_finetuner.py
signaturesnet/train_generator.py
signaturesnet/train_nummutnet.py
signaturesnet/configs/classifier/classifier.yaml
signaturesnet/configs/classifier/classifier_v2.yaml
signaturesnet/configs/errorfinder/errorfinder.yaml
signaturesnet/configs/errorfinder/errorfinder_v2.yaml
signaturesnet/configs/finetuner/finetuner_large.yaml
signaturesnet/configs/finetuner/finetuner_large_v2.yaml
signaturesnet/configs/finetuner/finetuner_low.yaml
signaturesnet/configs/finetuner/finetuner_low_v2.yaml
signaturesnet/configs/generator/generator.yaml
signaturesnet/configs/generator/generator_v2.yaml
signaturesnet/configs/nummutnet/nummutnet.yaml
signaturesnet/data/data.xlsx
signaturesnet/data/mutation_type_order.xlsx
signaturesnet/loggers/__init__.py
signaturesnet/loggers/classifier_logger.py
signaturesnet/loggers/errorfinder_logger.py
signaturesnet/loggers/finetuner_logger.py
signaturesnet/loggers/generator_logger.py
signaturesnet/loggers/nummut_logger.py
signaturesnet/models/__init__.py
signaturesnet/models/baseline.py
signaturesnet/models/classifier.py
signaturesnet/models/errorfinder.py
signaturesnet/models/finetuner.py
signaturesnet/models/generator.py
signaturesnet/models/nummut.py
signaturesnet/modules/__init__.py
signaturesnet/modules/classified_tunning_error.py
signaturesnet/modules/combined_finetuner.py
signaturesnet/modules/signet_module.py
signaturesnet/trained_models/detector/state_dict.zip
signaturesnet/trained_models/errorfinder/state_dict.zip
signaturesnet/trained_models/finetuner_large/state_dict.zip
signaturesnet/trained_models/finetuner_low/state_dict.zip
signaturesnet/trained_models/generator/state_dict.zip
signaturesnet/trained_models/nummutnet/state_dict.zip
signaturesnet/trainers/__init__.py
signaturesnet/trainers/classifier_trainer.py
signaturesnet/trainers/error_trainer.py
signaturesnet/trainers/finetuner_crossvalidation.py
signaturesnet-0.1.1.dist-info/LICENSE
signaturesnet-0.1.1.dist-info/METADATA
signaturesnet-0.1.1.dist-info/WHEEL
signaturesnet-0.1.1.dist-info/top_level.txt
signaturesnet-0.1.1.dist-info/RECORD
