Metadata-Version: 2.1
Name: signaturesnet
Version: 0.1.1
Summary: Package to manipulate mutational processes.
Home-page: https://github.com/weghornlab/SigNet
License-File: LICENSE
Requires-Dist: torch
Requires-Dist: scipy
Requires-Dist: numpy
Requires-Dist: matplotlib
Requires-Dist: pandas
Requires-Dist: seaborn
Requires-Dist: scikit-optimize
Requires-Dist: tqdm
Requires-Dist: pyparsing
Requires-Dist: PyYAML
Requires-Dist: scikit-learn
Requires-Dist: openpyxl
Requires-Dist: tensorboard
Requires-Dist: wandb
